climate_library/__init__.py
climate_library/climate_index.py
climate_library-1.0.0.dist-info/LICENSE.txt
climate_library-1.0.0.dist-info/METADATA
climate_library-1.0.0.dist-info/WHEEL
climate_library-1.0.0.dist-info/top_level.txt
climate_library-1.0.0.dist-info/RECORD
