Metadata-Version: 2.1
Name: climate-library
Version: 1.0.0
Summary: A library for calculating climate indices
Home-page: https://github.com/shiv3679/climate-indices
Author: Shiv Shankar Singh, Akshit Nanda
Author-email: shivshankarsingh.py@gmail.com
License: MIT
Classifier: Development Status :: 3 - Alpha
Classifier: Intended Audience :: Science/Research
Classifier: License :: OSI Approved :: MIT License
Classifier: Programming Language :: Python :: 3
Classifier: Programming Language :: Python :: 3.6
Classifier: Programming Language :: Python :: 3.7
Classifier: Programming Language :: Python :: 3.8
Classifier: Programming Language :: Python :: 3.9
License-File: LICENSE.txt
Requires-Dist: xarray
Requires-Dist: xclim
